Metadata-Version: 2.1
Name: odoo-addon-account_invoice_transmit_method
Version: 18.0.1.1.0
Requires-Python: >=3.10
Requires-Dist: odoo-addon-base_view_inheritance_extension==18.0.*
Requires-Dist: odoo==18.0.*
Summary: Configure invoice transmit method (email, post, portal, ...)
Home-page: https://github.com/OCA/account-invoicing
License: AGPL-3
Author: Akretion, Odoo Community Association (OCA)
Author-email: support@odoo-community.org
Classifier: Programming Language :: Python
Classifier: Framework :: Odoo
Classifier: Framework :: Odoo :: 18.0
Classifier: License :: OSI Approved :: GNU Affero General Public License v3
